examples/__init__.py
examples/basic_example.py
examples/matrix_example.py
examples/pop_synthesis_example.py
examples/pop_synthesis_example2.py
pyipu/__init__.py
pyipu/core.py
pyipu/synthesis.py
pyipu/utils.py
pyipu/version.py
pyipu-0.1.0.dist-info/licenses/LICENSE
tests/__init__.py
tests/test_ipu.py
pyipu-0.1.0.dist-info/METADATA
pyipu-0.1.0.dist-info/WHEEL
pyipu-0.1.0.dist-info/top_level.txt
pyipu-0.1.0.dist-info/RECORD
